src/there/__about__.py
src/there/__init__.py
src/there/connect_pois.py
src/there/index.py
src/there/index_oop.py
src/there/network.py
src/there/pois.py
src/there/visualise.py
there_access-0.1.1.dist-info/METADATA
there_access-0.1.1.dist-info/WHEEL
there_access-0.1.1.dist-info/licenses/LICENSE
there_access-0.1.1.dist-info/RECORD
