Metadata-Version: 2.1
Name: there-access
Version: 0.1.1
Summary: Multimodal access framework using OpenStreetMap data
Project-URL: Documentation, https://github.com/JosephineRoper/there#readme
Project-URL: Issues, https://github.com/JosephineRoper/there/issues
Project-URL: Source, https://github.com/JosephineRoper/there
Author-email: Josephine Roper <roper.josephine@gmail.com>
License-Expression: GPL-3.0-only
License-File: LICENSE
Classifier: Development Status :: 4 - Beta
Classifier: Programming Language :: Python
Classifier: Programming Language :: Python :: 3.8
Classifier: Programming Language :: Python :: 3.9
Classifier: Programming Language :: Python :: 3.10
Classifier: Programming Language :: Python :: 3.11
Classifier: Programming Language :: Python :: 3.12
Classifier: Programming Language :: Python :: Implementation :: CPython
Classifier: Programming Language :: Python :: Implementation :: PyPy
Requires-Python: >=3.8
